<?xml version="1.0" encoding="utf-8"?>
<!DOCTYPE hibernate-mapping PUBLIC "-//Hibernate/Hibernate Mapping DTD 3.0//EN"
"http://hibernate.sourceforge.net/hibernate-mapping-3.0.dtd">
<!-- 
    Mapping file autogenerated by MyEclipse Persistence Tools
-->
<hibernate-mapping>
    <class name="com.gacfinance.ycloans2.db.domain.LmLoan" table="LM_LOAN">
        <id name="loanNo" type="java.lang.String">
            <column name="LOAN_NO" length="30" />
            <generator class="assigned"></generator>
        </id>
        <property name="bankCde" type="java.lang.String">
            <column name="BANK_CDE" length="20" />
        </property>
        <property name="bchCde" type="java.lang.String">
            <column name="BCH_CDE" length="20" />
        </property>
        <property name="custId" type="java.lang.String">
            <column name="CUST_ID" length="30" />
        </property>
        <property name="custName" type="java.lang.String">
            <column name="CUST_NAME" length="200" />
        </property>
        <property name="loanTyp" type="java.lang.String">
            <column name="LOAN_TYP" length="10" />
        </property>
        <property name="loanSts" type="java.lang.String">
            <column name="LOAN_STS" length="10" />
        </property>
        <property name="tnr" type="java.lang.Short">
            <column name="TNR" precision="3" scale="0" />
        </property>
        <property name="lastDueDt" type="java.lang.String">
            <column name="LAST_DUE_DT" length="10" />
        </property>
        <property name="intStartDt" type="java.lang.String">
            <column name="INT_START_DT" length="10" />
        </property>
        <property name="loanDebtSts" type="java.lang.String">
            <column name="LOAN_DEBT_STS" length="5" />
        </property>
        <property name="dueDay" type="java.lang.Byte">
            <column name="DUE_DAY" precision="2" scale="0" />
        </property>
        <property name="loanOdInd" type="java.lang.String">
            <column name="LOAN_OD_IND" length="1" />
        </property>
        <property name="loanDevaInd" type="java.lang.String">
            <column name="LOAN_DEVA_IND" length="1" />
        </property>
        <property name="loanDevaDt" type="java.lang.String">
            <column name="LOAN_DEVA_DT" length="10" />
        </property>
        <property name="loanStpAccInd" type="java.lang.String">
            <column name="LOAN_STP_ACC_IND" length="1" />
        </property>
        <property name="loanStpAccDt" type="java.lang.String">
            <column name="LOAN_STP_ACC_DT" length="10" />
        </property>
        <property name="loanActvDt" type="java.lang.String">
            <column name="LOAN_ACTV_DT" length="10" />
        </property>
        <property name="rateBase" type="java.lang.String">
            <column name="RATE_BASE" length="1" />
        </property>
        <property name="loanIntRate" type="java.math.BigDecimal">
            <column name="LOAN_INT_RATE" precision="16" scale="9" />
        </property>
        <property name="loanOdIntRate" type="java.math.BigDecimal">
            <column name="LOAN_OD_INT_RATE" precision="16" scale="9" />
        </property>
        <property name="lastGenOdIntDt" type="java.lang.String">
            <column name="LAST_GEN_OD_INT_DT" length="10" />
        </property>
        <property name="lastIntAccDt" type="java.lang.String">
            <column name="LAST_INT_ACC_DT" length="10" />
        </property>
        <property name="lastSetlDt" type="java.lang.String">
            <column name="LAST_SETL_DT" length="10" />
        </property>
        <property name="curDueDt" type="java.lang.String">
            <column name="CUR_DUE_DT" length="10" />
        </property>
        <property name="nextDueDt" type="java.lang.String">
            <column name="NEXT_DUE_DT" length="10" />
        </property>
        <property name="paymFreqUnit" type="java.lang.String">
            <column name="PAYM_FREQ_UNIT" length="10" />
        </property>
        <property name="paymFreqFreq" type="java.lang.Short">
            <column name="PAYM_FREQ_FREQ" precision="3" scale="0" />
        </property>
        <property name="loanCcy" type="java.lang.String">
            <column name="LOAN_CCY" length="10" />
        </property>
        <property name="origPrcp" type="java.math.BigDecimal">
            <column name="ORIG_PRCP" precision="16" />
        </property>
        <property name="loanOsPrcp" type="java.math.BigDecimal">
            <column name="LOAN_OS_PRCP" precision="16" />
        </property>
        <property name="loanTnr" type="java.lang.Short">
            <column name="LOAN_TNR" precision="3" scale="0" />
        </property>
        <property name="loanOsDay" type="java.lang.Short">
            <column name="LOAN_OS_DAY" precision="3" scale="0" />
        </property>
        <property name="loanGlRoleCde" type="java.lang.String">
            <column name="LOAN_GL_ROLE_CDE" length="10" />
        </property>
        <property name="bussTyp" type="java.lang.String">
            <column name="BUSS_TYP" length="10" />
        </property>
        <property name="loanGrd" type="java.lang.String">
            <column name="LOAN_GRD" length="10" />
        </property>
        <property name="loanPaymMtd" type="java.lang.String">
            <column name="LOAN_PAYM_MTD" length="10" />
        </property>
        <property name="loanPaymTyp" type="java.lang.String">
            <column name="LOAN_PAYM_TYP" length="10" />
        </property>
        <property name="curGenOdIntDt" type="java.lang.String">
            <column name="CUR_GEN_OD_INT_DT" length="10" />
        </property>
        <property name="lastOdIntAccDt" type="java.lang.String">
            <column name="LAST_OD_INT_ACC_DT" length="10" />
        </property>
        <property name="prcsPageDtInd" type="java.lang.String">
            <column name="PRCS_PAGE_DT_IND" length="1" />
        </property>
        <property name="upVer" type="java.lang.Long">
            <column name="UP_VER" precision="16" scale="0" />
        </property>
        <property name="nextSynRateDt" type="java.lang.String">
            <column name="NEXT_SYN_RATE_DT" length="10" />
        </property>
        <property name="instmInd" type="java.lang.String">
            <column name="INSTM_IND" length="10" />
        </property>
        <property name="rlIntRate" type="java.math.BigDecimal">
            <column name="RL_INT_RATE" precision="16" scale="9" />
        </property>
        <property name="dnChannel" type="java.lang.String">
            <column name="DN_CHANNEL" length="60" />
        </property>
        <property name="paymChannel" type="java.lang.String">
            <column name="PAYM_CHANNEL" length="60" />
        </property>
        <property name="loanGraceTyp" type="java.lang.String">
            <column name="LOAN_GRACE_TYP" length="10" />
        </property>
        <property name="loanOdGrace" type="java.lang.Short">
            <column name="LOAN_OD_GRACE" precision="3" scale="0" />
        </property>
        <property name="loanOdIntGrace" type="java.lang.Short">
            <column name="LOAN_OD_INT_GRACE" precision="3" scale="0" />
        </property>
        <property name="thdCnt" type="java.lang.Byte">
            <column name="THD_CNT" precision="2" scale="0" not-null="true" />
        </property>
        <property name="atpySts" type="java.lang.String">
            <column name="ATPY_STS" length="10" />
        </property>
        <property name="intFreeDays" type="java.lang.Short">
            <column name="INT_FREE_DAYS" precision="3" scale="0" />
        </property>
        <property name="discIntRate" type="java.math.BigDecimal">
            <column name="DISC_INT_RATE" precision="16" scale="9" />
        </property>
        <property name="absLoanInd" type="java.lang.String">
            <column name="ABS_LOAN_IND" length="1" >
                 <comment>资产证券化贷款标识</comment>
            </column>
        </property>
        <property name="paymInd" type="java.lang.String">
            <column name="PAYM_IND" length="2" />
        </property>
        <property name="lastChgDt" type="java.lang.String">
            <column name="LAST_CHG_DT" length="10" />
        </property>
         <property name="intBase" type="java.lang.String">
            <column name="INT_BASE" length="10" />
        </property>
	<property name="vatRate" type="java.math.BigDecimal">
            <column name="VAT_RATE" precision="16" scale="9">
            	<comment>增值税税率</comment>
            </column>
        </property>
        <property name="perdType" type="java.lang.String">
            <column name="PERD_TYPE" length="5">
            	<comment>期限类型</comment>
            </column>
        </property>
        <property name="compInd" type="java.lang.String">
            <column name="COMP_IND" length="10" />
        </property>
        <property name="ddaPayTyp" type="java.lang.String">
          <column name="DDA_PAY_TYP" length="10" />
       </property>
       <property name="lastGenNormIntDt" type="java.lang.String">
            <column name="LAST_GEN_NORM_INT_DT" length="10" />
        </property>
        <property name="loanTypLine" type="java.lang.String">
            <column name="LOAN_TYP_LINE" length="10" />
        </property>
        <property name="notSetlTnr" type="java.lang.Short">
            <column name="NOT_SETL_TNR" precision="3" scale="0" />
        </property>
        <property name="settlementInd" type="java.lang.String">
            <column name="SETTLEMENT_IND" length="1" />
        </property>
        <property name="lastGenProdDt" type="java.lang.String">
            <column name="LAST_GEN_PROD_DT" length="10" />
        </property>
        <property name="grdMtdCde" type="java.lang.String">
            <column name="GRD_MTD_CDE" length="10" />
        </property>
        <property name="lastGrdDt" type="java.lang.String">
            <column name="LAST_GRD_DT" length="10" />
        </property>
        <property name="newGrdCde" type="java.lang.String">
            <column name="NEW_GRD_CDE" length="10" />
        </property>
        <property name="allOver" type="java.lang.String">
            <column name="ALL_OVER" length="1" />
        </property>
        <property name="prcpPlan" type="java.lang.String">
            <column name="PRCP_PLAN" length="1" />
        </property>
        <property name="isUnionSbsy" type="java.lang.String">
            <column name="IS_UNION_SBSY" length="1" />
        </property>
         <property name="isChangeTrial" type="java.lang.String">
            <column name="IS_CHANGE_TRIAL" length="1" />
        </property>
        <property name="isAdjSales" type="java.lang.String">
            <column name="IS_ADJ_SALES" length="1" />
        </property>
        <property name="forceStopInd" type="java.lang.String">
            <column name="FORCE_STOP_IND" length="1" />
        </property>
    </class>
</hibernate-mapping>
